_nuflux.cpython-311-x86_64-linux-gnu.so
nuflux/__init__.py
nuflux/data/SplineFlux/BERSS_H3a_central.fits
nuflux/data/SplineFlux/BERSS_H3p_central.fits
nuflux/data/SplineFlux/BERSS_H3p_lower.fits
nuflux/data/SplineFlux/BERSS_H3p_upper.fits
nuflux/data/SplineFlux2/H3a_SIBYLL21_conv_numubar.fits
nuflux/data/SplineFlux2/H3a_SIBYLL21_conv_nuebar.fits
nuflux/data/SplineFlux2/H3a_SIBYLL21_conv_numu.fits
nuflux/data/SplineFlux2/H3a_SIBYLL23C_nutau.fits
nuflux/data/SplineFlux2/H3a_SIBYLL23C_numubar.fits
nuflux/data/SplineFlux2/H3a_SIBYLL21_K0_nuebar.fits
nuflux/data/SplineFlux2/H3a_SIBYLL21_numubar.fits
nuflux/data/SplineFlux2/H3a_SIBYLL21_mu_nue.fits
nuflux/data/SplineFlux2/H3a_SIBYLL23C_K0_numubar.fits
nuflux/data/SplineFlux2/H3a_SIBYLL23C_pi_nue.fits
nuflux/data/SplineFlux2/H3a_SIBYLL21_conv_nue.fits
nuflux/data/SplineFlux2/H3a_SIBYLL21_K0L_numu.fits
nuflux/data/SplineFlux2/H3a_SIBYLL21_nuebar.fits
nuflux/data/SplineFlux2/H3a_SIBYLL23C_K0L_nuebar.fits
nuflux/data/SplineFlux2/H3a_SIBYLL23C_pr_nue.fits
nuflux/data/SplineFlux2/H3a_SIBYLL23C_K0L_numu.fits
nuflux/data/SplineFlux2/H3a_SIBYLL21_mu_numubar.fits
nuflux/data/SplineFlux2/H3a_SIBYLL23C_pr_numubar.fits
nuflux/data/SplineFlux2/H3a_SIBYLL23C_conv_numubar.fits
nuflux/data/SplineFlux2/H3a_SIBYLL21_k_nuebar.fits
nuflux/data/SplineFlux2/H3a_SIBYLL21_k_numubar.fits
nuflux/data/SplineFlux2/H3a_SIBYLL23C_mu_nue.fits
nuflux/data/SplineFlux2/H3a_SIBYLL23C_K0S_nuebar.fits
nuflux/data/SplineFlux2/H3a_SIBYLL21_K0S_nue.fits
nuflux/data/SplineFlux2/H3a_SIBYLL23C_pr_nuebar.fits
nuflux/data/SplineFlux2/H3a_SIBYLL21_nue.fits
nuflux/data/SplineFlux2/H3a_SIBYLL23C_K0_nuebar.fits
nuflux/data/SplineFlux2/H3a_SIBYLL21_k_nue.fits
nuflux/data/SplineFlux2/H3a_SIBYLL23C_pi_numubar.fits
nuflux/data/SplineFlux2/H3a_SIBYLL21_pi_nue.fits
nuflux/data/SplineFlux2/H3a_SIBYLL23C_pi_nuebar.fits
nuflux/data/SplineFlux2/H3a_SIBYLL23C_mu_nuebar.fits
nuflux/data/SplineFlux2/H3a_SIBYLL21_numu.fits
nuflux-2.0.7.dist-info/LICENSE
nuflux-2.0.7.dist-info/WHEEL
nuflux-2.0.7.dist-info/RECORD
nuflux-2.0.7.dist-info/METADATA
