Metadata-Version: 2.1
Name: nuflux
Version: 2.0.7
Summary: A library for calculating atmospheric neutrino fluxes
Keywords: python,science,astronomy,astrophysics,IceCube,atmospheric,neutrino
License:                    GNU LESSER GENERAL PUBLIC LICENSE
Classifier: Development Status :: 4 - Beta
Classifier: Intended Audience :: Developers
Classifier: Intended Audience :: Science/Research
Classifier: License :: OSI Approved :: GNU Lesser General Public License v3 or later (LGPLv3+)
Classifier: Operating System :: MacOS :: MacOS X
Classifier: Operating System :: POSIX :: Linux
Classifier: Programming Language :: C++
Classifier: Programming Language :: Python
Classifier: Programming Language :: Python :: 3.8
Classifier: Programming Language :: Python :: 3.9
Classifier: Programming Language :: Python :: 3.10
Classifier: Programming Language :: Python :: 3.11
Classifier: Topic :: Scientific/Engineering :: Astronomy
Classifier: Topic :: Scientific/Engineering :: Physics
Project-URL: Documentation, https://docs.icecube.aq/nuflux/main/
Project-URL: Source, https://github.com/icecube/nuflux
Project-URL: Collaboration, https://icecube.wisc.edu/
Project-URL: Doi, https://doi.org/10.5281/zenodo.8180337
Requires-Python: ~=3.7
Requires-Dist: numpy<2
Requires-Dist: pytest; extra == "test"
Requires-Dist: tbump; extra == "dev"
Provides-Extra: test
Provides-Extra: dev
